{
  "location": {
    "lat": 61.6245,
    "lon": 14.6994
  },
  "date": "2018-07-22",
  "cached_at": "2025-11-26T12:26:18.131321",
  "hours": [
    {
      "timestamp": 1532210400,
      "dateTimeISO": "2018-07-22T00:00:00+02:00",
      "tempC": 14.46,
      "dewpointC": 14.1,
      "humidity": 98,
      "windSpeedKPH": 4.61,
      "windGustKPH": 10.8,
      "precipMM": 0.58,
      "precipRateMM": 0.58,
      "pressureMB": 1007,
      "spressureMB": 963.2,
      "visibilityKM": null,
      "sky": 100,
      "uvi": null,
      "windDir": "NE",
      "weather": "Rain Showers",
      "feelslikeC": 14.46
    },
    {
      "timestamp": 1532214000,
      "dateTimeISO": "2018-07-22T01:00:00+02:00",
      "tempC": 14.16,
      "dewpointC": 13.76,
      "humidity": 97,
      "windSpeedKPH": 3.78,
      "windGustKPH": 6.66,
      "precipMM": 1.29,
      "precipRateMM": 1.29,
      "pressureMB": 1007,
      "spressureMB": 963.1,
      "visibilityKM": null,
      "sky": 100,
      "uvi": null,
      "windDir": "NE",
      "weather": "Showers",
      "feelslikeC": 14.16
    },
    {
      "timestamp": 1532217600,
      "dateTimeISO": "2018-07-22T02:00:00+02:00",
      "tempC": 13.72,
      "dewpointC": 13.56,
      "humidity": 99,
      "windSpeedKPH": 2.81,
      "windGustKPH": 5.4,
      "precipMM": 1.15,
      "precipRateMM": 1.15,
      "pressureMB": 1007,
      "spressureMB": 963.1,
      "visibilityKM": null,
      "sky": 100,
      "uvi": null,
      "windDir": "N",
      "weather": "Isolated Showers",
      "feelslikeC": 13.72
    },
    {
      "timestamp": 1532221200,
      "dateTimeISO": "2018-07-22T03:00:00+02:00",
      "tempC": 13.32,
      "dewpointC": 13.22,
      "humidity": 99,
      "windSpeedKPH": 4,
      "windGustKPH": 7.74,
      "precipMM": 0.57,
      "precipRateMM": 0.57,
      "pressureMB": 1007,
      "spressureMB": 963,
      "visibilityKM": null,
      "sky": 100,
      "uvi": null,
      "windDir": "NW",
      "weather": "Rain Showers",
      "feelslikeC": 13.32
    },
    {
      "timestamp": 1532224800,
      "dateTimeISO": "2018-07-22T04:00:00+02:00",
      "tempC": 13.22,
      "dewpointC": 13.12,
      "humidity": 99,
      "windSpeedKPH": 5.15,
      "windGustKPH": 10.8,
      "precipMM": 0.16,
      "precipRateMM": 0.16,
      "pressureMB": 1006,
      "spressureMB": 962,
      "visibilityKM": null,
      "sky": 100,
      "uvi": null,
      "windDir": "NW",
      "weather": "Rain Showers",
      "feelslikeC": 13.22
    },
    {
      "timestamp": 1532228400,
      "dateTimeISO": "2018-07-22T05:00:00+02:00",
      "tempC": 13.22,
      "dewpointC": 12.92,
      "humidity": 98,
      "windSpeedKPH": 6.77,
      "windGustKPH": 12.6,
      "precipMM": 0.04,
      "precipRateMM": 0.04,
      "pressureMB": 1006,
      "spressureMB": 962,
      "visibilityKM": null,
      "sky": 99,
      "uvi": null,
      "windDir": "NW",
      "weather": "Rain Showers",
      "feelslikeC": 13.22
    },
    {
      "timestamp": 1532232000,
      "dateTimeISO": "2018-07-22T06:00:00+02:00",
      "tempC": 13.99,
      "dewpointC": 13.52,
      "humidity": 97,
      "windSpeedKPH": 7.49,
      "windGustKPH": 16.2,
      "precipMM": 0,
      "precipRateMM": 0,
      "pressureMB": 1006,
      "spressureMB": 962.2,
      "visibilityKM": null,
      "sky": 86,
      "uvi": null,
      "windDir": "NNW",
      "weather": "Mostly Cloudy",
      "feelslikeC": 13.99
    },
    {
      "timestamp": 1532235600,
      "dateTimeISO": "2018-07-22T07:00:00+02:00",
      "tempC": 15.19,
      "dewpointC": 14.25,
      "humidity": 94,
      "windSpeedKPH": 8.86,
      "windGustKPH": 19.8,
      "precipMM": 0.09,
      "precipRateMM": 0.09,
      "pressureMB": 1006,
      "spressureMB": 962.3,
      "visibilityKM": null,
      "sky": 89,
      "uvi": null,
      "windDir": "NNW",
      "weather": "Showers",
      "feelslikeC": 15.19
    },
    {
      "timestamp": 1532239200,
      "dateTimeISO": "2018-07-22T08:00:00+02:00",
      "tempC": 15.96,
      "dewpointC": 14.61,
      "humidity": 92,
      "windSpeedKPH": 7.99,
      "windGustKPH": 21.6,
      "precipMM": 0.09,
      "precipRateMM": 0.09,
      "pressureMB": 1006,
      "spressureMB": 962.5,
      "visibilityKM": null,
      "sky": 96,
      "uvi": null,
      "windDir": "N",
      "weather": "Rain Showers",
      "feelslikeC": 15.96
    },
    {
      "timestamp": 1532242800,
      "dateTimeISO": "2018-07-22T09:00:00+02:00",
      "tempC": 17.06,
      "dewpointC": 14.12,
      "humidity": 83,
      "windSpeedKPH": 5.29,
      "windGustKPH": 18,
      "precipMM": 0.07,
      "precipRateMM": 0.07,
      "pressureMB": 1006,
      "spressureMB": 962.6,
      "visibilityKM": null,
      "sky": 100,
      "uvi": null,
      "windDir": "NNW",
      "weather": "Rain Showers",
      "feelslikeC": 17.06
    },
    {
      "timestamp": 1532246400,
      "dateTimeISO": "2018-07-22T10:00:00+02:00",
      "tempC": 18.15,
      "dewpointC": 14.16,
      "humidity": 78,
      "windSpeedKPH": 3.46,
      "windGustKPH": 15.66,
      "precipMM": 0.18,
      "precipRateMM": 0.18,
      "pressureMB": 1006,
      "spressureMB": 962.8,
      "visibilityKM": null,
      "sky": 97,
      "uvi": null,
      "windDir": "NW",
      "weather": "Rain Showers",
      "feelslikeC": 18.15
    },
    {
      "timestamp": 1532250000,
      "dateTimeISO": "2018-07-22T11:00:00+02:00",
      "tempC": 19.52,
      "dewpointC": 14.53,
      "humidity": 73,
      "windSpeedKPH": 3.71,
      "windGustKPH": 19.26,
      "precipMM": 0.09,
      "precipRateMM": 0.09,
      "pressureMB": 1006,
      "spressureMB": 963,
      "visibilityKM": null,
      "sky": 100,
      "uvi": null,
      "windDir": "WNW",
      "weather": "Rain Showers",
      "feelslikeC": 19.52
    },
    {
      "timestamp": 1532253600,
      "dateTimeISO": "2018-07-22T12:00:00+02:00",
      "tempC": 21.22,
      "dewpointC": 14.6,
      "humidity": 66,
      "windSpeedKPH": 5.94,
      "windGustKPH": 16.2,
      "precipMM": 0.1,
      "precipRateMM": 0.1,
      "pressureMB": 1006,
      "spressureMB": 963.2,
      "visibilityKM": null,
      "sky": 99,
      "uvi": null,
      "windDir": "WSW",
      "weather": "Rain Showers",
      "feelslikeC": 21.22
    },
    {
      "timestamp": 1532257200,
      "dateTimeISO": "2018-07-22T13:00:00+02:00",
      "tempC": 21.92,
      "dewpointC": 14.4,
      "humidity": 62,
      "windSpeedKPH": 6.19,
      "windGustKPH": 21.06,
      "precipMM": 0.12,
      "precipRateMM": 0.12,
      "pressureMB": 1005,
      "spressureMB": 962.4,
      "visibilityKM": null,
      "sky": 100,
      "uvi": null,
      "windDir": "SW",
      "weather": "Rain Showers",
      "feelslikeC": 21.92
    },
    {
      "timestamp": 1532260800,
      "dateTimeISO": "2018-07-22T14:00:00+02:00",
      "tempC": 22.62,
      "dewpointC": 14.47,
      "humidity": 60,
      "windSpeedKPH": 7.13,
      "windGustKPH": 18,
      "precipMM": 0.09,
      "precipRateMM": 0.09,
      "pressureMB": 1005,
      "spressureMB": 962.4,
      "visibilityKM": null,
      "sky": 98,
      "uvi": null,
      "windDir": "WSW",
      "weather": "Rain Showers",
      "feelslikeC": 22.62
    },
    {
      "timestamp": 1532264400,
      "dateTimeISO": "2018-07-22T15:00:00+02:00",
      "tempC": 22.95,
      "dewpointC": 14.34,
      "humidity": 58,
      "windSpeedKPH": 6.7,
      "windGustKPH": 19.8,
      "precipMM": 0.11,
      "precipRateMM": 0.11,
      "pressureMB": 1005,
      "spressureMB": 962.5,
      "visibilityKM": null,
      "sky": 78,
      "uvi": null,
      "windDir": "WSW",
      "weather": "Showers",
      "feelslikeC": 22.95
    },
    {
      "timestamp": 1532268000,
      "dateTimeISO": "2018-07-22T16:00:00+02:00",
      "tempC": 24.26,
      "dewpointC": 14.17,
      "humidity": 53,
      "windSpeedKPH": 6.48,
      "windGustKPH": 19.8,
      "precipMM": 0.1,
      "precipRateMM": 0.1,
      "pressureMB": 1005,
      "spressureMB": 962.7,
      "visibilityKM": null,
      "sky": 76,
      "uvi": null,
      "windDir": "SW",
      "weather": "Showers",
      "feelslikeC": 24.26
    },
    {
      "timestamp": 1532271600,
      "dateTimeISO": "2018-07-22T17:00:00+02:00",
      "tempC": 23.86,
      "dewpointC": 13.86,
      "humidity": 54,
      "windSpeedKPH": 6.66,
      "windGustKPH": 17.46,
      "precipMM": 0.08,
      "precipRateMM": 0.08,
      "pressureMB": 1005,
      "spressureMB": 962.6,
      "visibilityKM": null,
      "sky": 71,
      "uvi": null,
      "windDir": "SSW",
      "weather": "Showers",
      "feelslikeC": 23.86
    },
    {
      "timestamp": 1532275200,
      "dateTimeISO": "2018-07-22T18:00:00+02:00",
      "tempC": 23.86,
      "dewpointC": 13.86,
      "humidity": 54,
      "windSpeedKPH": 7.74,
      "windGustKPH": 14.4,
      "precipMM": 0,
      "precipRateMM": 0,
      "pressureMB": 1005,
      "spressureMB": 962.6,
      "visibilityKM": null,
      "sky": 56,
      "uvi": null,
      "windDir": "S",
      "weather": "Partly Cloudy",
      "feelslikeC": 23.86
    },
    {
      "timestamp": 1532278800,
      "dateTimeISO": "2018-07-22T19:00:00+02:00",
      "tempC": 23.39,
      "dewpointC": 13.46,
      "humidity": 54,
      "windSpeedKPH": 8.68,
      "windGustKPH": 12.6,
      "precipMM": 0,
      "precipRateMM": 0,
      "pressureMB": 1005,
      "spressureMB": 962.6,
      "visibilityKM": null,
      "sky": 46,
      "uvi": null,
      "windDir": "S",
      "weather": "Partly Cloudy",
      "feelslikeC": 23.39
    },
    {
      "timestamp": 1532282400,
      "dateTimeISO": "2018-07-22T20:00:00+02:00",
      "tempC": 22.89,
      "dewpointC": 13.59,
      "humidity": 56,
      "windSpeedKPH": 8.64,
      "windGustKPH": 10.26,
      "precipMM": 0,
      "precipRateMM": 0,
      "pressureMB": 1005,
      "spressureMB": 962.5,
      "visibilityKM": null,
      "sky": 43,
      "uvi": null,
      "windDir": "S",
      "weather": "Partly Cloudy",
      "feelslikeC": 22.89
    },
    {
      "timestamp": 1532286000,
      "dateTimeISO": "2018-07-22T21:00:00+02:00",
      "tempC": 21.32,
      "dewpointC": 13.56,
      "humidity": 61,
      "windSpeedKPH": 9.61,
      "windGustKPH": 16.2,
      "precipMM": 0,
      "precipRateMM": 0,
      "pressureMB": 1005,
      "spressureMB": 962.3,
      "visibilityKM": null,
      "sky": 38,
      "uvi": null,
      "windDir": "S",
      "weather": "Partly Cloudy",
      "feelslikeC": 21.32
    },
    {
      "timestamp": 1532289600,
      "dateTimeISO": "2018-07-22T22:00:00+02:00",
      "tempC": 19.12,
      "dewpointC": 12.99,
      "humidity": 68,
      "windSpeedKPH": 10.51,
      "windGustKPH": 18,
      "precipMM": 0,
      "precipRateMM": 0,
      "pressureMB": 1006,
      "spressureMB": 962.9,
      "visibilityKM": null,
      "sky": 44,
      "uvi": null,
      "windDir": "S",
      "weather": "Partly Cloudy",
      "feelslikeC": 19.12
    },
    {
      "timestamp": 1532293200,
      "dateTimeISO": "2018-07-22T23:00:00+02:00",
      "tempC": 17.39,
      "dewpointC": 12.39,
      "humidity": 72,
      "windSpeedKPH": 11.27,
      "windGustKPH": 19.8,
      "precipMM": 0,
      "precipRateMM": 0,
      "pressureMB": 1006,
      "spressureMB": 962.7,
      "visibilityKM": null,
      "sky": 24,
      "uvi": null,
      "windDir": "SSW",
      "weather": "Mostly Clear",
      "feelslikeC": 17.39
    }
  ]
}